README.md
setup.py
ntp_pool_score/__init__.py
ntp_pool_score/__main__.py
ntp_pool_score.egg-info/PKG-INFO
ntp_pool_score.egg-info/SOURCES.txt
ntp_pool_score.egg-info/dependency_links.txt
ntp_pool_score.egg-info/not-zip-safe
ntp_pool_score.egg-info/requires.txt
ntp_pool_score.egg-info/top_level.txt