Metadata-Version: 2.1
Name: ntp-pool-score
Version: 0.1
Summary: Retrieve the NTP pool score for a server
Home-page: https://www.github.com/rmcintosh/ntp_pool_score
Author: Richie McIntosh
Author-email: richiemcintosh@gmail.com
License: MIT
Platform: UNKNOWN
Requires-Python: >=3.8.0
